exodetbox/Brown2010DynamicCompletenessReplication.py
exodetbox/__init__.py
exodetbox/corey_dynamic_completeness.py
exodetbox/dynamicCompleteness.py
exodetbox/keithlyCompletenessConvergence.py
exodetbox/plotProjectedEllipse.py
exodetbox/projectedEllipse.py
exodetbox/testing_EXOSIMS_IAC.py
exodetbox/testing_projectedEllipse.py
exodetbox/convergence_data/Brown2010DynamicCompDataPickedFromFigure1.csv
exodetbox/convergence_data/Brown2010Lambert.pkl
exodetbox/convergence_data/Brown2010QuasiLambert.pkl
exodetbox/convergence_data/HabEx_CBrownKL_PPBrownKL_compSubtype.json
exodetbox/convergence_data/HabEx_CSAG13_PPSAG13_compSubtype.json
exodetbox/convergence_data/brownCompConvergence.csv
exodetbox/convergence_data/brownCompConvergence3.csv
exodetbox/convergence_data/keithlyCompConvergence.csv
exodetbox/scripts/HabEx_CBrownKL_PPBrownKL_IACintegrationScript.json
exo_det_box-0.0.2.dist-info/LICENSE
exo_det_box-0.0.2.dist-info/METADATA
exo_det_box-0.0.2.dist-info/WHEEL
exo_det_box-0.0.2.dist-info/top_level.txt
exo_det_box-0.0.2.dist-info/RECORD
